noticesl/__init__.py
noticesl/noticeapp.py
NoticeSlackLine-0.2.1b2.dist-info/METADATA
NoticeSlackLine-0.2.1b2.dist-info/WHEEL
NoticeSlackLine-0.2.1b2.dist-info/top_level.txt
NoticeSlackLine-0.2.1b2.dist-info/RECORD
